README.rst
setup.cfg
setup.py
djipsum/__init__.py
djipsum/faker.py
djipsum/fields.py
djipsum.egg-info/PKG-INFO
djipsum.egg-info/SOURCES.txt
djipsum.egg-info/dependency_links.txt
djipsum.egg-info/not-zip-safe
djipsum.egg-info/requires.txt
djipsum.egg-info/top_level.txt
djipsum/management/__init__.py
djipsum/management/commands/__init__.py
djipsum/management/commands/djipsum.py