Metadata-Version: 1.1
Name: djipsum
Version: 1.1.5
Summary: Django Lorem Ipsum Generator - Command plugin to generate (fake content data) for Django model.
Home-page: https://github.com/agusmakmun/djipsum/
Author: Agus Makmun (Summon Agus)
Author-email: agus@python.web.id
License: MIT
Download-URL: https://github.com/agusmakmun/djipsum/tarball/v1.1.5
Keywords: djipsum,django fake content data,django lorem ipsum generator,django unitest tool
Platform: UNKNOWN
Classifier: Programming Language :: Python
Classifier: Programming Language :: Python :: 2.7
Classifier: Programming Language :: Python :: 3.3
Classifier: Programming Language :: Python :: 3.4
Classifier: Programming Language :: Python :: 3.5
Classifier: License :: OSI Approved :: MIT License
Classifier: Operating System :: OS Independent
Classifier: Intended Audience :: Developers
Classifier: Framework :: Django
